README.md
setup.py
ojcrawler/__init__.py
ojcrawler/control.py
ojcrawler/utils.py
ojcrawler.egg-info/PKG-INFO
ojcrawler.egg-info/SOURCES.txt
ojcrawler.egg-info/dependency_links.txt
ojcrawler.egg-info/requires.txt
ojcrawler.egg-info/top_level.txt
ojcrawler/crawlers/__init__.py
ojcrawler/crawlers/base.py
ojcrawler/crawlers/codeforces.py
ojcrawler/crawlers/config.py
ojcrawler/crawlers/hdu.py
ojcrawler/crawlers/poj.py
ojcrawler/tests/__init__.py
ojcrawler/tests/test_get_problem.py
ojcrawler/tests/test_submit.py
ojcrawler/tests/test_sync_func.py