Metadata-Version: 1.1
Name: ojcrawler
Version: 1.1.9
Summary: crawler of some online judge system
Home-page: https://github.com/LETTersOnline/ojcrawler
Author: crazyX
Author-email: xu_jingwei@outlook.com
License: MIT
Platform: UNKNOWN
Classifier: Programming Language :: Python :: 3
Classifier: License :: OSI Approved :: MIT License
Classifier: Operating System :: OS Independent
